sagellm/__init__.py
sagellm/__init__.pyc
sagellm/cli.pyc
sagellm/py.typed
sagellm/__pycache__/__init__.cpython-311.pyc
sagellm/__pycache__/cli.cpython-311.pyc
isagellm-0.4.1.2.dist-info/METADATA
isagellm-0.4.1.2.dist-info/WHEEL
isagellm-0.4.1.2.dist-info/entry_points.txt
isagellm-0.4.1.2.dist-info/top_level.txt
isagellm-0.4.1.2.dist-info/RECORD
