Metadata-Version: 2.4
Name: isagellm
Version: 0.4.1.2
Summary: sageLLM: Modular LLM inference engine with PD separation for domestic computing power
Author: IntelliStream Team
License: Proprietary - IntelliStream
Project-URL: Homepage, https://github.com/IntelliStream/sagellm
Project-URL: Documentation, https://github.com/IntelliStream/sagellm#readme
Project-URL: Repository, https://github.com/IntelliStream/sagellm
Keywords: llm,inference,ascend,huawei,npu,cuda,domestic,pd-separation
Classifier: Development Status :: 3 - Alpha
Classifier: Programming Language :: Python :: 3
Classifier: Programming Language :: Python :: 3.10
Classifier: Programming Language :: Python :: 3.11
Classifier: Programming Language :: Python :: 3.12
Classifier: Topic :: Scientific/Engineering :: Artificial Intelligence
Requires-Python: ==3.11.*
Requires-Dist: isagellm-protocol<0.5.0,>=0.4.0.7
Requires-Dist: isagellm-backend<0.5.0,>=0.4.0.8
Requires-Dist: isagellm-core<0.5.0,>=0.4.0.11
Requires-Dist: isagellm-control-plane<0.5.0,>=0.4.0.7
Requires-Dist: isagellm-gateway<0.5.0,>=0.4.0.7
Requires-Dist: isagellm-kv-cache<0.5.0,>=0.4.0.7
Requires-Dist: isagellm-comm<0.5.0,>=0.4.0.6
Requires-Dist: isagellm-compression<0.5.0,>=0.4.0.6
Requires-Dist: click>=8.0.0
Requires-Dist: rich>=13.0.0
Requires-Dist: pyyaml>=6.0.0
Provides-Extra: dev
Requires-Dist: pytest>=7.0.0; extra == "dev"
Requires-Dist: pytest-cov>=4.0.0; extra == "dev"
Requires-Dist: ruff>=0.8.0; extra == "dev"
Requires-Dist: mypy>=1.0.0; extra == "dev"
Requires-Dist: isage-pypi-publisher>=0.2.0; extra == "dev"
